Metadata-Version: 2.1
Name: weaklabels
Version: 0.0.1.dev1
Summary: Python library with tools dealing with weak labels.
Home-page: https://github.com/Orieus/WeakLabelModel
Author: Jesus Cid Sueiro, Miquel Perello Nieto, Daniel Bacaicoa
Author-email: perello.nieto@gmail.com
License: UNKNOWN
Download-URL: https://github.com/Orieus/WeakLabelModel/archive/0.0.1.dev1.tar.gz
Keywords: machine learning,classification,supervised,weak labels,noisy labels
Platform: UNKNOWN
